userbot_auth/__init__.py
userbot_auth/__version__.py
userbot_auth/client.py
userbot_auth/utils.py
userbot_auth-1.0.12.dist-info/licenses/LICENSE
userbot_auth-1.0.12.dist-info/METADATA
userbot_auth-1.0.12.dist-info/WHEEL
userbot_auth-1.0.12.dist-info/top_level.txt
userbot_auth-1.0.12.dist-info/RECORD
