Metadata-Version: 2.4
Name: userbot_auth
Version: 1.0.12
Summary: Ryzenth UBT | Enterprise Security Framework.
Author: TeamKillerX
License: MIT
Project-URL: Source, https://github.com/TeamKillerX/Userbot-Auth/
Project-URL: Issues, https://github.com/TeamKillerX/Userbot-Auth/issues
Keywords: Userbot-Auth-API,Ryzenth-SDK
Classifier: Programming Language :: Python :: 3
Classifier: Programming Language :: Python :: 3.7
Classifier: Programming Language :: Python :: 3.8
Classifier: Programming Language :: Python :: 3.9
Classifier: Programming Language :: Python :: 3.10
Classifier: Programming Language :: Python :: 3.11
Classifier: Development Status :: 5 - Production/Stable
Classifier: License :: OSI Approved :: MIT License
Classifier: Operating System :: OS Independent
Classifier: Intended Audience :: Developers
Classifier: Natural Language :: English
Requires-Python: ~=3.7
License-File: LICENSE
Requires-Dist: requests
Requires-Dist: aiohttp
Dynamic: author
Dynamic: classifier
Dynamic: description
Dynamic: description-content-type
Dynamic: keywords
Dynamic: license
Dynamic: license-file
Dynamic: project-url
Dynamic: requires-dist
Dynamic: requires-python
Dynamic: summary
